occ2vec/__init__.py
occ2vec/settings.py
occ2vec/data/__init__.py
occ2vec/data/embedding_data/onet_embeddings.parquet
occ2vec/data/onet_data/__init__.py
occ2vec/data/onet_data/prepared/attributes.parquet
occ2vec/data/onet_data/prepared/tasks.parquet
occ2vec/nlp/__init__.py
occ2vec/nlp/nlp.py
occ2vec/onet/__init__.py
occ2vec/onet/dates.py
occ2vec/onet/onet.py
occ2vec/onet/tools.py
occ2vec/utils/__init__.py
occ2vec-0.0.9.dist-info/LICENSE
occ2vec-0.0.9.dist-info/METADATA
occ2vec-0.0.9.dist-info/WHEEL
occ2vec-0.0.9.dist-info/top_level.txt
occ2vec-0.0.9.dist-info/RECORD
