Metadata-Version: 2.1
Name: occ2vec
Version: 0.0.9
Summary: Occ2vec paper
Home-page: https://github.com/muhlbach/occ2vec
Author: Nicolaj Søndergaard Mühlbach
Author-email: n.muhlbach@gmail.com
License: MIT License
Keywords: text embeddings,natural language processing,deep learning,machine learning
Platform: UNKNOWN
Classifier: Programming Language :: Python :: 3
Classifier: License :: OSI Approved :: MIT License
Classifier: Operating System :: OS Independent
Requires-Python: >=3.6
License-File: LICENSE
Requires-Dist: bodyguard (>=0.0.9)
